ambition/__init__.py
ambition/api_client.py
ambition/configuration.py
ambition/rest.py
ambition/version.py
ambition/apis/__init__.py
ambition/apis/account_api.py
ambition/apis/base_api.py
ambition/apis/data_api.py
ambition/models/__init__.py
ambition/models/account_api_serializer.py
ambition/models/depot_serializer.py
ambition/models/public_api_data_create_response.py
ambition/models/public_api_data_list_response.py
ambition/models/serializer.py
ambition/models/write_account_api_serializer.py
ambition/models/write_depot_serializer.py
ambition/models/write_serializer.py
ambition/tests/__init__.py
ambition/tests/api_client_tests.py
ambition/tests/rest_tests.py
ambition-0.1.2.dist-info/DESCRIPTION.rst
ambition-0.1.2.dist-info/METADATA
ambition-0.1.2.dist-info/metadata.json
ambition-0.1.2.dist-info/pbr.json
ambition-0.1.2.dist-info/RECORD
ambition-0.1.2.dist-info/top_level.txt
ambition-0.1.2.dist-info/WHEEL
