Metadata-Version: 2.0
Name: ambition
Version: 0.1.2
Summary: UNKNOWN
Home-page: https://github.com/ambitioninc/ambition
Author: Ryan Bales
Author-email: opensource@ambition.com
License: MIT
Platform: UNKNOWN
Classifier: Programming Language :: Python :: 2.7
Classifier: Programming Language :: Python :: 3.3
Classifier: Programming Language :: Python :: 3.4
Classifier: Intended Audience :: Developers
Classifier: License :: OSI Approved :: MIT License
Classifier: Operating System :: OS Independent
Requires-Dist: urllib3 (>=1.10)
Requires-Dist: six (>=1.9)
Requires-Dist: certifi
Requires-Dist: python-dateutil (==2.4.2)
